shipout/__init__.py
shipout/infra_utils/pulumi_util.py
shipout/main.py
shipout-0.1.2.dist-info/entry_points.txt
shipout-0.1.2.dist-info/WHEEL
shipout-0.1.2.dist-info/METADATA
shipout-0.1.2.dist-info/RECORD
