Metadata-Version: 2.1
Name: shipout
Version: 0.1.2
Summary: 
Author: BlurwareAdmin
Author-email: admin@blurware.com
Requires-Python: >=3.8,<4.0
Classifier: Programming Language :: Python :: 3
Classifier: Programming Language :: Python :: 3.10
Classifier: Programming Language :: Python :: 3.8
Classifier: Programming Language :: Python :: 3.9
Requires-Dist: azure-identity (>=1.10.0,<2.0.0)
Requires-Dist: azure-mgmt-authorization (>=2.0.0,<3.0.0)
Requires-Dist: azure-mgmt-resource (>=21.1.0,<22.0.0)
Requires-Dist: azure-mgmt-storage (>=20.0.0,<21.0.0)
Requires-Dist: docker (>=5.0.3,<6.0.0)
Requires-Dist: pulumi (>=3.33.1,<4.0.0)
Requires-Dist: pulumi-azure (>=5.10.0,<6.0.0)
Requires-Dist: pulumi-azure-native (>=1.64.1,<2.0.0)
Requires-Dist: typer[all] (>=0.4.1,<0.5.0)
